scholarversary/__init__.py
scholarversary-0.1.0.dist-info/METADATA
scholarversary-0.1.0.dist-info/WHEEL
scholarversary-0.1.0.dist-info/RECORD
