Metadata-Version: 2.3
Name: scholarversary
Version: 0.1.0
Summary: Add your description here
Requires-Python: >=3.11
Requires-Dist: httpx>=0.27.2
